did/__init__.py
did/base.py
did/cli.py
did/stats.py
did/utils.py
did/plugins/__init__.py
did/plugins/bodhi.py
did/plugins/bugzilla.py
did/plugins/confluence.py
did/plugins/footer.py
did/plugins/gerrit.py
did/plugins/git.py
did/plugins/github.py
did/plugins/gitlab.py
did/plugins/google.py
did/plugins/header.py
did/plugins/hyperkitty.py
did/plugins/items.py
did/plugins/jira.py
did/plugins/koji.py
did/plugins/nitrate.py
did/plugins/pagure.py
did/plugins/phabricator.py
did/plugins/public_inbox.py
did/plugins/redmine.py
did/plugins/rt.py
did/plugins/sentry.py
did/plugins/trac.py
did/plugins/trello.py
did/plugins/wiki.py
did/plugins/zammad.py
did-0.22.1.data/scripts/did
did-0.22.1.dist-info/licenses/LICENSE
did-0.22.1.dist-info/METADATA
did-0.22.1.dist-info/WHEEL
did-0.22.1.dist-info/top_level.txt
did-0.22.1.dist-info/RECORD
