Metadata-Version: 2.4
Name: did
Version: 0.22.1
Summary: did - What did you do last week, month, year?
Home-page: https://github.com/psss/did
Download-URL: https://github.com/psss/did/archive/master.zip
Author: Petr Šplíchal
Author-email: psplicha@redhat.com
Maintainer: Petr Šplíchal
Maintainer-email: psplicha@redhat.com
License: GPL-2.0-or-later
Keywords: status,report,tasks,work
Classifier: Natural Language :: English
Classifier: Programming Language :: Python :: 3.9
Classifier: Programming Language :: Python :: 3.10
Classifier: Programming Language :: Python :: 3.11
Classifier: Programming Language :: Python :: 3.12
Classifier: Programming Language :: Python :: 3.13
Classifier: Topic :: Office/Business
Classifier: Topic :: Utilities
Provides: did
License-File: LICENSE
Requires-Dist: python_dateutil
Requires-Dist: requests
Requires-Dist: requests-gssapi
Requires-Dist: tenacity
Requires-Dist: urllib3
Provides-Extra: bodhi
Requires-Dist: bodhi-client; extra == "bodhi"
Provides-Extra: bugzilla
Requires-Dist: python-bugzilla; extra == "bugzilla"
Provides-Extra: docs
Requires-Dist: sphinx==8.2.3; extra == "docs"
Requires-Dist: sphinx-rtd-theme==3.0.2; extra == "docs"
Provides-Extra: google
Requires-Dist: google-api-python-client; extra == "google"
Requires-Dist: oauth2client; extra == "google"
Provides-Extra: jira
Requires-Dist: requests_gssapi; extra == "jira"
Provides-Extra: koji
Requires-Dist: koji; extra == "koji"
Provides-Extra: redmine
Requires-Dist: feedparser; extra == "redmine"
Provides-Extra: nitrate
Requires-Dist: nitrate; extra == "nitrate"
Provides-Extra: rt
Requires-Dist: gssapi; extra == "rt"
Provides-Extra: tests
Requires-Dist: pytest; extra == "tests"
Requires-Dist: pytest-xdist; extra == "tests"
Requires-Dist: pytest-cov; extra == "tests"
Requires-Dist: python-coveralls; extra == "tests"
Requires-Dist: pre-commit; extra == "tests"
Provides-Extra: all
Requires-Dist: bodhi-client; extra == "all"
Requires-Dist: python-bugzilla; extra == "all"
Requires-Dist: sphinx==8.2.3; extra == "all"
Requires-Dist: sphinx-rtd-theme==3.0.2; extra == "all"
Requires-Dist: google-api-python-client; extra == "all"
Requires-Dist: oauth2client; extra == "all"
Requires-Dist: requests_gssapi; extra == "all"
Requires-Dist: koji; extra == "all"
Requires-Dist: feedparser; extra == "all"
Requires-Dist: nitrate; extra == "all"
Requires-Dist: gssapi; extra == "all"
Requires-Dist: pytest; extra == "all"
Requires-Dist: pytest-xdist; extra == "all"
Requires-Dist: pytest-cov; extra == "all"
Requires-Dist: python-coveralls; extra == "all"
Requires-Dist: pre-commit; extra == "all"
Dynamic: author
Dynamic: author-email
Dynamic: classifier
Dynamic: description
Dynamic: download-url
Dynamic: home-page
Dynamic: keywords
Dynamic: license
Dynamic: license-file
Dynamic: maintainer
Dynamic: maintainer-email
Dynamic: provides
Dynamic: provides-extra
Dynamic: requires-dist
Dynamic: summary
